Workbook

Sheet About
A1: Financial Statement Analysis (sample)
A3: Purpose: calculate common ratios from an income statement and balance sheet for two years and describe how the business changed.
A4: The company, 'Sample Retail Co.', and all numbers are FICTIONAL and were created for practice. They are not from any real company.
A5: Tabs: Statements (inputs and subtotals), Ratios (formulas and year-over-year change).
A6: Colors: blue text = typed-in inputs, black text = formulas, yellow fill = assumption cells you can change.
A7: Units: US dollars in thousands.
A8: Simplifications: ROE and inventory turnover use year-end balances instead of averages, and the tax rate is a flat assumption.

Sheet Statements
A1: Sample Retail Co. - Financial Statements ($ in thousands, fictional)
A2: Income tax rate (assumption) | B2: 0.25
A4: Income Statement | B4: FY2024 | C4: FY2025
A5: Revenue | B5: 2000 | C5: 2300
A6: Cost of goods sold | B6: 1300 | C6: 1450
A7: Gross profit | B7: =B5-B6 -> 700 | C7: =C5-C6 -> 850
A8: Operating expenses | B8: 450 | C8: 520
A9: Operating income | B9: =B7-B8 -> 250 | C9: =C7-C8 -> 330
A10: Interest expense | B10: 30 | C10: 28
A11: Income before tax | B11: =B9-B10 -> 220 | C11: =C9-C10 -> 302
A12: Income tax expense | B12: =ROUND(B11*$B$2,0) -> 55 | C12: =ROUND(C11*$B$2,0) -> 76
A13: Net income | B13: =B11-B12 -> 165 | C13: =C11-C12 -> 226
A15: Balance Sheet | B15: FY2024 | C15: FY2025
A16: Cash | B16: 150 | C16: 180
A17: Accounts receivable | B17: 110 | C17: 120
A18: Inventory | B18: 240 | C18: 260
A19: Total current assets | B19: =SUM(B16:B18) -> 500 | C19: =SUM(C16:C18) -> 560
A20: Property and equipment, net | B20: 600 | C20: 640
A21: Total assets | B21: =B19+B20 -> 1100 | C21: =C19+C20 -> 1200
A22: Accounts payable | B22: 130 | C22: 140
A23: Short-term debt | B23: 50 | C23: 60
A24: Total current liabilities | B24: =B22+B23 -> 180 | C24: =C22+C23 -> 200
A25: Long-term debt | B25: 320 | C25: 300
A26: Total liabilities | B26: =B24+B25 -> 500 | C26: =C24+C25 -> 500
A27: Shareholders' equity | B27: 600 | C27: 700
A28: Total liabilities and equity | B28: =B26+B27 -> 1100 | C28: =C26+C27 -> 1200
A29: Balance check (assets - liabilities and equity) | B29: =B21-B28 -> 0 | C29: =C21-C28 -> 0

Sheet Ratios
A1: Ratio Analysis
A3: Ratio | B3: FY2024 | C3: FY2025 | D3: Change | E3: Direction
A4: Gross margin | B4: =Statements!B7/Statements!B5 -> 0.35 | C4: =Statements!C7/Statements!C5 -> 0.36956522 | D4: =C4-B4 -> 0.019565217 | E4: =IF(ABS(D4)<0.00005,"Flat",IF(D4>0,"Up","Down")) -> Up
A5: Operating margin | B5: =Statements!B9/Statements!B5 -> 0.125 | C5: =Statements!C9/Statements!C5 -> 0.14347826 | D5: =C5-B5 -> 0.018478261 | E5: =IF(ABS(D5)<0.00005,"Flat",IF(D5>0,"Up","Down")) -> Up
A6: Net profit margin | B6: =Statements!B13/Statements!B5 -> 0.0825 | C6: =Statements!C13/Statements!C5 -> 0.09826087 | D6: =C6-B6 -> 0.01576087 | E6: =IF(ABS(D6)<0.00005,"Flat",IF(D6>0,"Up","Down")) -> Up
A7: Current ratio | B7: =Statements!B19/Statements!B24 -> 2.7777778 | C7: =Statements!C19/Statements!C24 -> 2.8 | D7: =C7-B7 -> 0.022222222 | E7: =IF(ABS(D7)<0.00005,"Flat",IF(D7>0,"Up","Down")) -> Up
A8: Quick ratio | B8: =(Statements!B16+Statements!B17)/Statements!B24 -> 1.4444444 | C8: =(Statements!C16+Statements!C17)/Statements!C24 -> 1.5 | D8: =C8-B8 -> 0.055555556 | E8: =IF(ABS(D8)<0.00005,"Flat",IF(D8>0,"Up","Down")) -> Up
A9: Debt-to-equity | B9: =Statements!B26/Statements!B27 -> 0.83333333 | C9: =Statements!C26/Statements!C27 -> 0.71428571 | D9: =C9-B9 -> -0.11904762 | E9: =IF(ABS(D9)<0.00005,"Flat",IF(D9>0,"Up","Down")) -> Down
A10: Return on equity | B10: =Statements!B13/Statements!B27 -> 0.275 | C10: =Statements!C13/Statements!C27 -> 0.32285714 | D10: =C10-B10 -> 0.047857143 | E10: =IF(ABS(D10)<0.00005,"Flat",IF(D10>0,"Up","Down")) -> Up
A11: Inventory turnover | B11: =Statements!B6/Statements!B18 -> 5.4166667 | C11: =Statements!C6/Statements!C18 -> 5.5769231 | D11: =C11-B11 -> 0.16025641 | E11: =IF(ABS(D11)<0.00005,"Flat",IF(D11>0,"Up","Down")) -> Up
A12: Revenue growth (FY2025 vs FY2024) | C12: =Statements!C5/Statements!B5-1 -> 0.15
A14: How to read: margins and returns going up is generally favorable; debt-to-equity going down means less leverage. 'Direction' only shows the sign of the change, not whether it is good.
