Workbook

Sheet About
A1: Payroll Reconciliation (sample)
A3: Purpose: compare one pay period's payroll register to what was posted in the general ledger (GL), and flag differences to investigate.
A4: All data is FICTIONAL sample data created for practice. No real company, employee, or payroll information is used.
A5: Tabs: Payroll Register (source data + tax calculations), GL Postings (what the books show), Reconciliation (comparison and status).
A6: Colors: blue text = typed-in input values, black text = formulas, yellow fill = assumption cells you can change.
A7: Simplified assumptions: Social Security 6.2% and Medicare 1.45% for both employee and employer; no wage base limit, state taxes, or benefits.
A8: The sample GL contains one deliberate error (a bonus that was not posted) so the reconciliation has something to catch.

Sheet Payroll Register
A1: Payroll Register - Pay Period Ending 2026-09-15 (fictional data)
A3: Social Security rate | B3: 0.062
A4: Medicare rate | B4: 0.0145
A6: Employee ID | B6: Employee | C6: Gross Wages | D6: Federal Income Tax W/H | E6: Employee Social Security | F6: Employee Medicare | G6: Employer Social Security | H6: Employer Medicare | I6: Net Pay
A7: E101 | B7: Employee 01 | C7: 4200 | D7: 520 | E7: =ROUND(C7*$B$3,2) -> 260.4 | F7: =ROUND(C7*$B$4,2) -> 60.9 | G7: =ROUND(C7*$B$3,2) -> 260.4 | H7: =ROUND(C7*$B$4,2) -> 60.9 | I7: =C7-D7-E7-F7 -> 3358.7
A8: E102 | B8: Employee 02 | C8: 3850 | D8: 430 | E8: =ROUND(C8*$B$3,2) -> 238.7 | F8: =ROUND(C8*$B$4,2) -> 55.83 | G8: =ROUND(C8*$B$3,2) -> 238.7 | H8: =ROUND(C8*$B$4,2) -> 55.83 | I8: =C8-D8-E8-F8 -> 3125.47
A9: E103 | B9: Employee 03 | C9: 5100 | D9: 690 | E9: =ROUND(C9*$B$3,2) -> 316.2 | F9: =ROUND(C9*$B$4,2) -> 73.95 | G9: =ROUND(C9*$B$3,2) -> 316.2 | H9: =ROUND(C9*$B$4,2) -> 73.95 | I9: =C9-D9-E9-F9 -> 4019.85
A10: E104 | B10: Employee 04 | C10: 2900 | D10: 260 | E10: =ROUND(C10*$B$3,2) -> 179.8 | F10: =ROUND(C10*$B$4,2) -> 42.05 | G10: =ROUND(C10*$B$3,2) -> 179.8 | H10: =ROUND(C10*$B$4,2) -> 42.05 | I10: =C10-D10-E10-F10 -> 2418.15
A11: E105 | B11: Employee 05 | C11: 4600 | D11: 585 | E11: =ROUND(C11*$B$3,2) -> 285.2 | F11: =ROUND(C11*$B$4,2) -> 66.7 | G11: =ROUND(C11*$B$3,2) -> 285.2 | H11: =ROUND(C11*$B$4,2) -> 66.7 | I11: =C11-D11-E11-F11 -> 3663.1
A12: E106 | B12: Employee 06 | C12: 6200 | D12: 880 | E12: =ROUND(C12*$B$3,2) -> 384.4 | F12: =ROUND(C12*$B$4,2) -> 89.9 | G12: =ROUND(C12*$B$3,2) -> 384.4 | H12: =ROUND(C12*$B$4,2) -> 89.9 | I12: =C12-D12-E12-F12 -> 4845.7
A13: E107 | B13: Employee 07 | C13: 3300 | D13: 335 | E13: =ROUND(C13*$B$3,2) -> 204.6 | F13: =ROUND(C13*$B$4,2) -> 47.85 | G13: =ROUND(C13*$B$3,2) -> 204.6 | H13: =ROUND(C13*$B$4,2) -> 47.85 | I13: =C13-D13-E13-F13 -> 2712.55
A14: E108 | B14: Employee 08 | C14: 3950 | D14: 445 | E14: =ROUND(C14*$B$3,2) -> 244.9 | F14: =ROUND(C14*$B$4,2) -> 57.28 | G14: =ROUND(C14*$B$3,2) -> 244.9 | H14: =ROUND(C14*$B$4,2) -> 57.28 | I14: =C14-D14-E14-F14 -> 3202.82
A15: E109 | B15: Employee 09 | C15: 4800 | D15: 640 | E15: =ROUND(C15*$B$3,2) -> 297.6 | F15: =ROUND(C15*$B$4,2) -> 69.6 | G15: =ROUND(C15*$B$3,2) -> 297.6 | H15: =ROUND(C15*$B$4,2) -> 69.6 | I15: =C15-D15-E15-F15 -> 3792.8
A16: E110 | B16: Employee 10 | C16: 5400 | D16: 745 | E16: =ROUND(C16*$B$3,2) -> 334.8 | F16: =ROUND(C16*$B$4,2) -> 78.3 | G16: =ROUND(C16*$B$3,2) -> 334.8 | H16: =ROUND(C16*$B$4,2) -> 78.3 | I16: =C16-D16-E16-F16 -> 4241.9
B17: Total | C17: =SUM(C7:C16) -> 44300 | D17: =SUM(D7:D16) -> 5530 | E17: =SUM(E7:E16) -> 2746.6 | F17: =SUM(F7:F16) -> 642.36 | G17: =SUM(G7:G16) -> 2746.6 | H17: =SUM(H7:H16) -> 642.36 | I17: =SUM(I7:I16) -> 35381.04

Sheet GL Postings
A1: General Ledger Postings - same pay period (fictional data)
A3: GL Account | B3: Description | C3: Amount
A4: Wages Expense | B4: Gross wages posted to the GL | C4: 43050
A5: Payroll Tax Expense | B5: Employer Social Security + Medicare | C5: 3388.96
A6: Payroll Liabilities - Withholdings | B6: Federal W/H + employee Social Security + employee Medicare | C6: 8918.96
A8: Note: amounts above are typed-in sample data (blue). In real work these come from the GL detail report.

Sheet Reconciliation
A1: Reconciliation: Payroll Register vs. General Ledger
A2: Tolerance ($) | B2: 0.01
A4: Item | B4: Payroll Register | C4: General Ledger | D4: Variance (GL - Register) | E4: Status
A5: Gross wages | B5: ='Payroll Register'!C17 -> 44300 | C5: ='GL Postings'!C4 -> 43050 | D5: =C5-B5 -> -1250 | E5: =IF(ABS(D5)<=$B$2,"Matches","Investigate") -> Investigate
A6: Employer payroll taxes | B6: ='Payroll Register'!G17+'Payroll Register'!H17 -> 3388.96 | C6: ='GL Postings'!C5 -> 3388.96 | D6: =C6-B6 -> 0 | E6: =IF(ABS(D6)<=$B$2,"Matches","Investigate") -> Matches
A7: Employee withholdings | B7: ='Payroll Register'!D17+'Payroll Register'!E17+'Payroll Register'!F17 -> 8918.96 | C7: ='GL Postings'!C6 -> 8918.96 | D7: =C7-B7 -> 0 | E7: =IF(ABS(D7)<=$B$2,"Matches","Investigate") -> Matches
A9: Items to investigate | B9: =COUNTIF(E5:E7,"Investigate") -> 1
A11: Analyst notes (sample)
A12: Gross wages are lower in the GL than in the register. The difference equals one bonus payment that was paid through payroll but not posted.
A13: Suggested fix: an adjusting journal entry, debit Wages Expense and credit the payroll clearing/cash account for the variance amount.
A14: Prevention: reconcile each payroll run to the GL before closing the period, and review any variance above the tolerance.
